rpitwit
