Metadata-Version: 1.0
Name: rpitwit
Version: 0.2.0
Summary: Remote control your RaspberryPI from Twitter.
Home-page: http://pypi.python.org/pypi/RPiTwit/
Author: Mario Gomez
Author-email: mxgxw.alpha@gmail.com
License: LICENSE.txt
Platform: UNKNOWN
